{
  "tutorial": {
    "id": 2608,
    "version": 9,
    "type": "guidedProject",
    "isNew": false,
    "codeLanguage": "html",
    "title": "Trivia Game - Part 2",
    "descriptionContent": "With the logic in place, now, it's all about player engagement. We'll spruce up our game, introducing multiple questions and displaying a score.",
    "shortDescriptionContent": "",
    "showInTrack": true,
    "iconBanner": "tutorial-2608-icon-banner.svg",
    "chapters": [
      {
        "id": 14459,
        "title": "Project Part 2: More questions",
        "type": "practiceLevel3",
        "lessons": [
          {
            "title": "Lesson #1",
            "id": 128880,
            "contentType": "executableFiles",
            "images": [],
            "executableContent": {
              "instructions": "Welcome to the second part of our **Trivia Game** project, where we'll add more questions and extend our game logic.\n\n1. To start, transform your `question` variable into an array called `questions` with multiple strings. If you need another idea for a question, what about `\"Who painted the Mona Lisa?\"`?\n2. Create a new variable named `currentQuestionIndex ` and set its value to `0`.\n3. Inside the `displayQuestion` function, access the correct element of the new array `questions` by using the `currentQuestionIndex` as the index; do this instead of directly assigning the `question` element the value of the variable `question`.",
              "preselectedFileIndex": 2,
              "hasVisualOutput": true,
              "files": [
                {
                  "name": "index.html",
                  "codeLanguage": "html",
                  "content": "<!doctype html>\n<html>\n<head>\n  <title>Simple Trivia</title>\n  <link rel=\"stylesheet\" href=\"style.css\">\n</head>\n<body>\n  <div class=\"container\">\n    <h1>Simple Trivia</h1>\n    <h2 id=\"question\"></h2>\n    <div id=\"choices\">\n      <button id=\"choice1\" onclick=\"checkAnswer(this)\"></button>\n      <button id=\"choice2\" onclick=\"checkAnswer(this)\"></button>\n      <button id=\"choice3\" onclick=\"checkAnswer(this)\"></button>\n      <button id=\"choice4\" onclick=\"checkAnswer(this)\"></button>\n    </div>\n  <div id=\"result\"></div>\n</div>\n  <script src=\"script.js\"></script>\n</body>\n</html>",
                  "solvedContent": null
                },
                {
                  "name": "style.css",
                  "codeLanguage": "css",
                  "content": "",
                  "solvedContent": null
                },
                {
                  "name": "script.js",
                  "codeLanguage": "javascript",
                  "content": "const question = \"What planet is known as the 'Red Planet'?\";\nconst choices = [\"Earth\", \"Mars\", \"Jupiter\", \"Saturn\"];\nconst correctAnswer = \"Mars\";\n\nfunction displayQuestion() {\n  document.getElementById('question').innerHTML = question;\n  for (let i = 0; i < choices.length; i++){\n    const btn = document.getElementById(`choice${i+1}`);\n    btn.innerHTML = choices[i];\n    btn.value = choices[i];\n  }\n}\n\nfunction checkAnswer(button) {\n  if (button.value === correctAnswer) {\n    document.getElementById('result').innerHTML = \"Correct!\";\n  } else {\n    document.getElementById('result').innerHTML = \"Wrong!\";\n  }\n  for(let i = 1; i <= 4; i++){\n    document.getElementById(`choice${i}`).disabled = true;\n  }\n}\n\ndisplayQuestion();",
                  "solvedContent": "const questions = [\"What planet is known as the 'Red Planet'?\",\n\"Who painted the Mona Lisa?\"];\nconst choices = [\"Earth\", \"Mars\", \"Jupiter\", \"Saturn\"];\nconst correctAnswer = \"Mars\";\n\nlet currentQuestionIndex = 0;\n\nfunction displayQuestion() {\n  document.getElementById('question').innerHTML = questions[currentQuestionIndex];\n  for (let i = 0; i < choices.length; i++){\n    const btn = document.getElementById(`choice${i+1}`);\n    btn.innerHTML = choices[i];\n    btn.value = choices[i];\n  }\n}\n\nfunction checkAnswer(button) {\n  if (button.value === correctAnswer) {\n    document.getElementById('result').innerHTML = \"Correct!\";\n  } else {\n    document.getElementById('result').innerHTML = \"Wrong!\";\n  }\n  for(let i = 1; i <= 4; i++){\n    document.getElementById(`choice${i}`).disabled = true;\n  }\n}\n\ndisplayQuestion();"
                }
              ],
              "hints": []
            }
          },
          {
            "title": "Lesson #2",
            "id": 128881,
            "contentType": "executableFiles",
            "images": [],
            "executableContent": {
              "instructions": "Next, we must update our `choices` and `correctAnswer` variables to consider multiple questions.\n\n1. Create two arrays that are called `choicesArray` and `correctAnswers`.\n2. In `choicesArray`, each item should be an array containing four answers to the corresponding trivia question.\n3. In `correctAnswers`, each item should be a string that is the correct answer to the corresponding trivia question.\n4. Remove the old `choices` and `correctAnswer` variables as we no longer need them.\n\nThese changes will momentarily break our web page. Don't worry, we'll fix it soon.",
              "preselectedFileIndex": 2,
              "hasVisualOutput": true,
              "files": [
                {
                  "name": "index.html",
                  "codeLanguage": "html",
                  "content": "<!doctype html>\n<html>\n<head>\n  <title>Simple Trivia</title>\n  <link rel=\"stylesheet\" href=\"style.css\">\n</head>\n<body>\n  <div class=\"container\">\n    <h1>Simple Trivia</h1>\n    <h2 id=\"question\"></h2>\n    <div id=\"choices\">\n      <button id=\"choice1\" onclick=\"checkAnswer(this)\"></button>\n      <button id=\"choice2\" onclick=\"checkAnswer(this)\"></button>\n      <button id=\"choice3\" onclick=\"checkAnswer(this)\"></button>\n      <button id=\"choice4\" onclick=\"checkAnswer(this)\"></button>\n    </div>\n  <div id=\"result\"></div>\n</div>\n  <script src=\"script.js\"></script>\n</body>\n</html>",
                  "solvedContent": null
                },
                {
                  "name": "style.css",
                  "codeLanguage": "css",
                  "content": "",
                  "solvedContent": null
                },
                {
                  "name": "script.js",
                  "codeLanguage": "javascript",
                  "content": "const questions = [\"What planet is known as the 'Red Planet'?\",\n\"Who painted the Mona Lisa?\"];\nconst choices = [\"Earth\", \"Mars\", \"Jupiter\", \"Saturn\"];\nconst correctAnswer = \"Mars\";\n\nlet currentQuestionIndex = 0;\n\nfunction displayQuestion() {\n  document.getElementById('question').innerHTML = questions[currentQuestionIndex];\n  for (let i = 0; i < choices.length; i++){\n    const btn = document.getElementById(`choice${i+1}`);\n    btn.innerHTML = choices[i];\n    btn.value = choices[i];\n  }\n}\n\nfunction checkAnswer(button) {\n  if (button.value === correctAnswer) {\n    document.getElementById('result').innerHTML = \"Correct!\";\n  } else {\n    document.getElementById('result').innerHTML = \"Wrong!\";\n  }\n  for(let i = 1; i <= 4; i++){\n    document.getElementById(`choice${i}`).disabled = true;\n  }\n}\n\ndisplayQuestion();",
                  "solvedContent": "const questions = [\"What planet is known as the 'Red Planet'?\",\n\"Who painted the Mona Lisa?\"];\nconst choicesArray = [\n    [\"Earth\", \"Mars\", \"Jupiter\", \"Saturn\"],\n    [\"Van Gogh\", \"Picasso\", \"Da Vinci\", \"Rembrandt\"]\n];\n\nconst correctAnswers = [\"Mars\", \"Da Vinci\"];\n\nlet currentQuestionIndex = 0;\n\nfunction displayQuestion() {\n  document.getElementById('question').innerHTML = questions[currentQuestionIndex];\n  for (let i = 0; i < choices.length; i++){\n    const btn = document.getElementById(`choice${i+1}`);\n    btn.innerHTML = choices[i];\n    btn.value = choices[i];\n  }\n}\n\nfunction checkAnswer(button) {\n  if (button.value === correctAnswer) {\n    document.getElementById('result').innerHTML = \"Correct!\";\n  } else {\n    document.getElementById('result').innerHTML = \"Wrong!\";\n  }\n  for(let i = 1; i <= 4; i++){\n    document.getElementById(`choice${i}`).disabled = true;\n  }\n}\n\ndisplayQuestion();"
                }
              ],
              "hints": [
                {
                  "title": "How should the arrays look?",
                  "content": "```JavaScript\nconst questions = [\n  \"What planet is known as the 'Red Planet'?\",\n  \"Who painted the Mona Lisa?\"\n];\n\nconst choicesArray = [\n  [\"Earth\", \"Mars\", \"Jupiter\", \"Saturn\"],\n  [\"Van Gogh\", \"Picasso\", \"Da Vinci\", \"Rembrandt\"]\n];\n\nconst correctAnswers = [\"Mars\", \"Da Vinci\"];\n```"
                }
              ]
            }
          },
          {
            "title": "Lesson #3",
            "id": 128904,
            "contentType": "executableFiles",
            "images": [],
            "executableContent": {
              "instructions": "It's time to display the choices correctly again. \n\n1. Update the assignment of `innerHTML` and `value` inside the for loop in the `displayQuestion` function to set the right choices. Use `choicesArray[currentQuestionIndex][i]` to first access the correct array for the question and then the correct choice instead of `choices[i]`.",
              "preselectedFileIndex": 2,
              "hasVisualOutput": true,
              "files": [
                {
                  "name": "index.html",
                  "codeLanguage": "html",
                  "content": "<!doctype html>\n<html>\n<head>\n  <title>Simple Trivia</title>\n  <link rel=\"stylesheet\" href=\"style.css\">\n</head>\n<body>\n  <div class=\"container\">\n    <h1>Simple Trivia</h1>\n    <h2 id=\"question\"></h2>\n    <div id=\"choices\">\n      <button id=\"choice1\" onclick=\"checkAnswer(this)\"></button>\n      <button id=\"choice2\" onclick=\"checkAnswer(this)\"></button>\n      <button id=\"choice3\" onclick=\"checkAnswer(this)\"></button>\n      <button id=\"choice4\" onclick=\"checkAnswer(this)\"></button>\n    </div>\n  <div id=\"result\"></div>\n</div>\n  <script src=\"script.js\"></script>\n</body>\n</html>",
                  "solvedContent": null
                },
                {
                  "name": "style.css",
                  "codeLanguage": "css",
                  "content": "",
                  "solvedContent": null
                },
                {
                  "name": "script.js",
                  "codeLanguage": "javascript",
                  "content": "const questions = [\"What planet is known as the 'Red Planet'?\",\n\"Who painted the Mona Lisa?\"];\nconst choicesArray = [\n    [\"Earth\", \"Mars\", \"Jupiter\", \"Saturn\"],\n    [\"Van Gogh\", \"Picasso\", \"Da Vinci\", \"Rembrandt\"]\n];\n\nconst correctAnswers = [\"Mars\", \"Da Vinci\"];\n\nlet currentQuestionIndex = 0;\n\nfunction displayQuestion() {\n  document.getElementById('question').innerHTML = questions[currentQuestionIndex];\n  for (let i = 0; i < 4; i++) {\n    const btn = document.getElementById(`choice${i+1}`);\n    btn.innerHTML = choices[i];\n    btn.value = choices[i];\n  }\n}\n\nfunction checkAnswer(button) {\n  if (button.value === correctAnswer) {\n    document.getElementById('result').innerHTML = \"Correct!\";\n  } else {\n    document.getElementById('result').innerHTML = \"Wrong!\";\n  }\n  for(let i = 1; i <= 4; i++){\n    document.getElementById(`choice${i}`).disabled = true;\n  }\n}\n\ndisplayQuestion();",
                  "solvedContent": "const questions = [\"What planet is known as the 'Red Planet'?\",\n\"Who painted the Mona Lisa?\"];\nconst choicesArray = [\n    [\"Earth\", \"Mars\", \"Jupiter\", \"Saturn\"],\n    [\"Van Gogh\", \"Picasso\", \"Da Vinci\", \"Rembrandt\"]\n];\n\nconst correctAnswers = [\"Mars\", \"Da Vinci\"];\n\nlet currentQuestionIndex = 0;\n\nfunction displayQuestion() {\n  document.getElementById('question').innerHTML = questions[currentQuestionIndex];\n  for (let i = 0; i < 4; i++) {\n    const btn = document.getElementById(`choice${i+1}`);\n    btn.innerHTML = choicesArray[currentQuestionIndex][i];\n    btn.value = choicesArray[currentQuestionIndex][i];\n  }\n}\n\nfunction checkAnswer(button) {\n  if (button.value === correctAnswer) {\n    document.getElementById('result').innerHTML = \"Correct!\";\n  } else {\n    document.getElementById('result').innerHTML = \"Wrong!\";\n  }\n  for(let i = 1; i <= 4; i++){\n    document.getElementById(`choice${i}`).disabled = true;\n  }\n}\n\ndisplayQuestion();"
                }
              ],
              "hints": []
            }
          },
          {
            "title": "Lesson #4",
            "id": 128885,
            "contentType": "executableFiles",
            "images": [],
            "executableContent": {
              "instructions": "As we now have multiple questions, let's display more than just one.\n\n1. Wrap all of your code in the displayQuestion function in an if block.\n2. Check if the `currentQuestionIndex` is still smaller than the number of elements in the `questions` variable.\n3. Add an else block.\n4. In this else block, display the player's final score and disable the choice buttons. Use `document.getElementById` to target the element where the result will be displayed. \n5.  Set the elements `innerHTML` to show the score.\n6. Remove the question by setting the `innerHTML` of the element with the id `question` to an empty string.\n7. Then, remove all buttons by setting the `innerHTML` of the `div` with the id `choices` to an empty string.",
              "preselectedFileIndex": 2,
              "hasVisualOutput": true,
              "files": [
                {
                  "name": "index.html",
                  "codeLanguage": "html",
                  "content": "<!doctype html>\n<html>\n<head>\n  <title>Simple Trivia</title>\n  <link rel=\"stylesheet\" href=\"style.css\">\n</head>\n<body>\n  <div class=\"container\">\n    <h1>Simple Trivia</h1>\n    <h2 id=\"question\"></h2>\n    <div id=\"choices\">\n      <button id=\"choice1\" onclick=\"checkAnswer(this)\"></button>\n      <button id=\"choice2\" onclick=\"checkAnswer(this)\"></button>\n      <button id=\"choice3\" onclick=\"checkAnswer(this)\"></button>\n      <button id=\"choice4\" onclick=\"checkAnswer(this)\"></button>\n    </div>\n  <div id=\"result\"></div>\n</div>\n  <script src=\"script.js\"></script>\n</body>\n</html>",
                  "solvedContent": null
                },
                {
                  "name": "style.css",
                  "codeLanguage": "css",
                  "content": "",
                  "solvedContent": null
                },
                {
                  "name": "script.js",
                  "codeLanguage": "javascript",
                  "content": "const questions = [\"What planet is known as the 'Red Planet'?\",\n  \"Who painted the Mona Lisa?\"\n];\nconst choicesArray = [\n  [\"Earth\", \"Mars\", \"Jupiter\", \"Saturn\"],\n  [\"Van Gogh\", \"Picasso\", \"Da Vinci\", \"Rembrandt\"]\n];\nconst correctAnswers = [\"Mars\", \"Da Vinci\"];\nlet currentQuestionIndex = 0;\n\nfunction displayQuestion() {\n  document.getElementById('question').innerHTML = questions[\n    currentQuestionIndex];\n  for (let i = 0; i < 4; i++) {\n    const btn = document.getElementById(`choice${i+1}`);\n    btn.innerHTML = choicesArray[currentQuestionIndex][i];\n    btn.value = choicesArray[currentQuestionIndex][i];\n  }\n}\n\nfunction checkAnswer(button) {\n  if (button.value === correctAnswer) {\n    document.getElementById('result').innerHTML = \"Correct!\";\n  } else {\n    document.getElementById('result').innerHTML = \"Wrong!\";\n  }\n  for (let i = 1; i <= 4; i++) {\n    document.getElementById(`choice${i}`).disabled = true;\n  }\n}\ndisplayQuestion();",
                  "solvedContent": "const questions = [\"What planet is known as the 'Red Planet'?\",\n  \"Who painted the Mona Lisa?\"\n];\nconst choicesArray = [\n  [\"Earth\", \"Mars\", \"Jupiter\", \"Saturn\"],\n  [\"Van Gogh\", \"Picasso\", \"Da Vinci\", \"Rembrandt\"]\n];\nconst correctAnswers = [\"Mars\", \"Da Vinci\"];\nlet currentQuestionIndex = 0;\n\nfunction displayQuestion() {\n  if (currentQuestionIndex < questions.length) {\n    document.getElementById('question').innerHTML = questions[\n      currentQuestionIndex];\n    for (let i = 0; i < 4; i++) {\n    const btn = document.getElementById(`choice${i+1}`);\n    btn.innerHTML = choicesArray[currentQuestionIndex][i];\n    btn.value = choicesArray[currentQuestionIndex][i];\n  }\n  } else {\n    document.getElementById('result').innerHTML =\n      `You scored ${score} out of ${questions.length}!`;\n      document.getElementById('question').innerHTML = \"\";\n      document.getElementById('choices').innerHTML = \"\";\n  }\n}\n\nfunction checkAnswer(button) {\n  if (button.value === correctAnswer) {\n    document.getElementById('result').innerHTML = \"Correct!\";\n  } else {\n    document.getElementById('result').innerHTML = \"Wrong!\";\n  }\n  for (let i = 1; i <= 4; i++) {\n    document.getElementById(`choice${i}`).disabled = true;\n  }\n}\ndisplayQuestion();"
                }
              ],
              "hints": []
            }
          },
          {
            "title": "Lesson #5",
            "id": 128886,
            "contentType": "executableFiles",
            "images": [],
            "executableContent": {
              "instructions": "Lastly, we'll update the function to verify the player's chosen answer.\n\n1. Define a new `score` variable at the top of the file and set it to `0`.\n2. Remove all the code from the function `checkAnswer()`.\n3. In this `checkAnswer()` function, add an if statement to check if the `value` of the `button` parameter is equal to the current correct answer by retrieving the correct answer from the `correctAnswers` array using the `currentQuestionIndex`.\n4. If it is, increment `score` by `1`.\n5. After the if statement, increment `currentQuestionIndex` by `1`.\n6. At the very end of the function, call the `displayQuestion()` function to display the next question.",
              "preselectedFileIndex": 2,
              "hasVisualOutput": true,
              "files": [
                {
                  "name": "index.html",
                  "codeLanguage": "html",
                  "content": "<!doctype html>\n<html>\n<head>\n  <title>Simple Trivia</title>\n  <link rel=\"stylesheet\" href=\"style.css\">\n</head>\n<body>\n  <div class=\"container\">\n    <h1>Simple Trivia</h1>\n    <h2 id=\"question\"></h2>\n    <div id=\"choices\">\n      <button id=\"choice1\" onclick=\"checkAnswer(this)\"></button>\n      <button id=\"choice2\" onclick=\"checkAnswer(this)\"></button>\n      <button id=\"choice3\" onclick=\"checkAnswer(this)\"></button>\n      <button id=\"choice4\" onclick=\"checkAnswer(this)\"></button>\n    </div>\n  <div id=\"result\"></div>\n</div>\n  <script src=\"script.js\"></script>\n</body>\n</html>",
                  "solvedContent": null
                },
                {
                  "name": "style.css",
                  "codeLanguage": "css",
                  "content": "",
                  "solvedContent": null
                },
                {
                  "name": "script.js",
                  "codeLanguage": "javascript",
                  "content": "const questions = [\"What planet is known as the 'Red Planet'?\",\n  \"Who painted the Mona Lisa?\"\n];\nconst choicesArray = [\n  [\"Earth\", \"Mars\", \"Jupiter\", \"Saturn\"],\n  [\"Van Gogh\", \"Picasso\", \"Da Vinci\", \"Rembrandt\"]\n];\nconst correctAnswers = [\"Mars\", \"Da Vinci\"];\nlet currentQuestionIndex = 0;\n\nfunction displayQuestion() {\n  if (currentQuestionIndex < questions.length) {\n    document.getElementById('question').innerHTML = questions[\n      currentQuestionIndex];\n    for (let i = 0; i < 4; i++) {\n    const btn = document.getElementById(`choice${i+1}`);\n    btn.innerHTML = choicesArray[currentQuestionIndex][i];\n    btn.value = choicesArray[currentQuestionIndex][i];\n  }\n    } else {\n    document.getElementById('result').innerHTML =\n      `You scored ${score} out of ${questions.length}!`;\n      document.getElementById('question').innerHTML = \"\";\n      document.getElementById('choices').innerHTML = \"\";\n  }\n}\n\nfunction checkAnswer(button) {\n  if (button.value === correctAnswer) {\n    document.getElementById('result').innerHTML = \"Correct!\";\n  } else {\n    document.getElementById('result').innerHTML = \"Wrong!\";\n  }\n  for (let i = 1; i <= 4; i++) {\n    document.getElementById(`choice${i}`).disabled = true;\n  }\n}\ndisplayQuestion();",
                  "solvedContent": "const questions = [\"What planet is known as the 'Red Planet'?\",\n  \"Who painted the Mona Lisa?\"\n];\nconst choicesArray = [\n  [\"Earth\", \"Mars\", \"Jupiter\", \"Saturn\"],\n  [\"Van Gogh\", \"Picasso\", \"Da Vinci\", \"Rembrandt\"]\n];\nconst correctAnswers = [\"Mars\", \"Da Vinci\"];\nlet currentQuestionIndex = 0;\nlet score = 0;\n\nfunction displayQuestion() {\n  if (currentQuestionIndex < questions.length) {\n    document.getElementById('question').innerHTML = questions[\n      currentQuestionIndex];\n    for (let i = 0; i < 4; i++) {\n    const btn = document.getElementById(`choice${i+1}`);\n    btn.innerHTML = choicesArray[currentQuestionIndex][i];\n    btn.value = choicesArray[currentQuestionIndex][i];\n  }\n    } else {\n    document.getElementById('result').innerHTML =\n      `You scored ${score} out of ${questions.length}!`;\n      document.getElementById('question').innerHTML = \"\";\n      document.getElementById('choices').innerHTML = \"\";\n  }\n}\n\nfunction checkAnswer(button) {\n  if (button.value === correctAnswers[currentQuestionIndex]) {\n        score++;\n    }\n    currentQuestionIndex++;\n    displayQuestion();\n}\ndisplayQuestion();"
                }
              ],
              "hints": []
            }
          },
          {
            "title": "Lesson #6",
            "id": 128888,
            "contentType": "executableFiles",
            "images": [],
            "executableContent": {
              "instructions": "Let's add some color. Style the page as you want. If you need some ideas, feel free to do the following. We'll style 5 aspects of our webpage: `body`, `container`, `button`, `button:hover`, and `result`.\n\n1. In the `body`, set the font-family to `\"Arial\", sans-serif`,  set the background to a linear gradient, set the height to `100vh`, set the `display` mode to `flex`, set `align-items` and `justify-content` to `center`, and text alignment to `center`, too.\n2. In the `.container`, set the `background` to `white`, the border radius to a value that suits you, the `width` to `90%`, the max width to a value you like, add a box shadow and padding.\n3. For the `button`, specify the padding, margin, background color, text color, border, border radius, and set `cursor-style` to `pointer`.\n4. For `button:hover`, set the background color  to a different one.\n5. Lastly, set the `margin-top`, `font-weight`, `font-size`, and `color` in `#result`.",
              "preselectedFileIndex": 1,
              "hasVisualOutput": true,
              "files": [
                {
                  "name": "index.html",
                  "codeLanguage": "html",
                  "content": "<!doctype html>\n<html>\n<head>\n    <title>Trivia Game</title>\n    <link rel=\"stylesheet\" href=\"style.css\">\n</head>\n<body>\n    <div class=\"container\">\n        <h1>Trivia Game</h1>\n        <h2 id=\"question\"></h2>\n        <div id=\"choices\">\n            <button id=\"choice1\" onclick=\"checkAnswer(this)\"></button>\n            <button id=\"choice2\" onclick=\"checkAnswer(this)\"></button>\n            <button id=\"choice3\" onclick=\"checkAnswer(this)\"></button>\n            <button id=\"choice4\" onclick=\"checkAnswer(this)\"></button>\n        </div>\n        <div id=\"result\"></div>\n    </div>\n    <script src=\"script.js\"></script>\n</body>\n</html>",
                  "solvedContent": null
                },
                {
                  "name": "style.css",
                  "codeLanguage": "css",
                  "content": "",
                  "solvedContent": "body {\n    font-family: 'Arial', sans-serif;\n    background: linear-gradient(45deg, teal, white);\n    height: 100vh;\n    display: flex;\n    align-items: center;\n    justify-content: center;\n    text-align: center;\n}\n\n.container {\n    background: white;\n    border-radius: 10px;\n    width: 90%;\n    max-width: 600px;\n    box-shadow: 0 5px 15px rgba(0, 0, 0, 0.2);\n    padding: 12px;\n}\n\nbutton {\n    padding: 10px 20px;\n    background-color: slategray;\n    color: white;\n    border: none;\n    border-radius: 5px;\n    cursor: pointer;\n    margin: 10px;\n    transition: background-color 0.3s, transform 0.3s;\n}\n\nbutton:hover {\n    background-color: teal;\n    transform: scale(1.05);\n}\n\n#result {\n    margin-top: 20px;\n    font-weight: bold;\n    font-size: 1.3rem;\n    color: teal;\n}"
                },
                {
                  "name": "script.js",
                  "codeLanguage": "javascript",
                  "content": "const questions = [\n    \"What's the capital of France?\", \n    \"Who painted the Mona Lisa?\"\n];\n\nconst choicesArray = [\n    [\"Paris\", \"London\", \"Berlin\", \"Madrid\"], \n    [\"Van Gogh\", \"Picasso\", \"Da Vinci\", \"Rembrandt\"]\n];\n\nconst correctAnswers = [\"Paris\", \"Da Vinci\"];\n\nlet currentQuestionIndex = 0;\nlet score = 0;\n\nfunction displayQuestion() {\n    if (currentQuestionIndex < questions.length) {\n        document.getElementById('question').innerHTML = questions[currentQuestionIndex];\n        for (let i = 0; i < 4; i++) {\n            const btn = document.getElementById(`choice${i+1}`);\n            btn.innerHTML = choicesArray[currentQuestionIndex][i];\n            btn.value = choicesArray[currentQuestionIndex][i];\n        }\n      } else {\n    document.getElementById('result').innerHTML =\n      `You scored ${score} out of ${questions.length}!`;\n      document.getElementById('question').innerHTML = \"\";\n      document.getElementById('choices').innerHTML = \"\";\n  }\n}\n\nfunction checkAnswer(btn) {\n    if (btn.value === correctAnswers[currentQuestionIndex]) {\n        score++;\n    }\n    currentQuestionIndex++;\n    displayQuestion();\n}\n\ndisplayQuestion();",
                  "solvedContent": null
                }
              ],
              "hints": []
            }
          }
        ]
      }
    ]
  }
}