{
  "tutorial": {
    "id": 2923,
    "version": 1,
    "type": "course",
    "isNew": false,
    "codeLanguage": "node",
    "title": "Datenbankeinrichtung",
    "descriptionContent": "Lerne, wie man eine Datenbankdatei in Express mit SQLite einrichtet",
    "shortDescriptionContent": "",
    "showInTrack": true,
    "iconBanner": null,
    "chapters": [
      {
        "id": 15028,
        "title": "Kapitel #1",
        "type": "practiceLevel1",
        "lessons": [
          {
            "title": "Lesson #1",
            "id": 132534,
            "contentType": "interactive",
            "images": [],
            "interactiveContent": "<!DOCTYPE html ><html><body><p>Lass uns eintauchen, wie wir Daten mit einem separaten <code>database.js</code>-Modul verwalten können, um die Datenbankinteraktion innerhalb unserer Express-App zu erleichtern.</p></body></html>"
          },
          {
            "title": "Lesson #2",
            "id": 132535,
            "contentType": "interactive",
            "images": [],
            "interactiveContent": "<!DOCTYPE html ><html><body><p>Zuerst müssen wir unsere Datenbank einrichten. In unserer <code>database.js</code>-Datei benötigen wir das <code>better-sqlite3</code>-Modul und definieren unseren Datenbankdateinamen.</p><code version=\"2\" codelang=\"javascript\" name=\"database.js\" visible-if=\"always\"><content><text value=\"const\" class=\"keyword\" /><text value=\" Database = \" /><text value=\"require\" class=\"built_in\" /><text value=\"(\" /><text value=\"&quot;better-sqlite3&quot;\" class=\"string\" /><text value=\");\" /><text type=\"break\" /><text value=\"const\" class=\"keyword\" /><text value=\" db = \" /><text value=\"new\" class=\"keyword\" /><text value=\" Database(\" /><text value=\"&quot;database.db&quot;\" class=\"string\" /><text value=\");\" /></content><interactions><interaction type=\"fillTheGap\" isDefault=\"true\"><options><option startIndex=\"17\" endIndex=\"24\" /><option startIndex=\"25\" endIndex=\"41\" /><option startIndex=\"68\" endIndex=\"81\" /></options></interaction></interactions></code><p visible-if=\"wrong\">Wähle <code>require</code>, gefolgt von <code>\"better-sqlite3\"</code> und schließlich <code>\"database.db\"</code> aus.</p></body></html>"
          },
          {
            "title": "Lesson #3 - Copy",
            "id": 132541,
            "contentType": "interactive",
            "images": [],
            "interactiveContent": "<!DOCTYPE html ><html><body><p>Als nächstes richten wir unsere Tabellen ein. Wir können <code>db.exec</code> verwenden, um die Anweisung auszuführen, und <code>CREATE TABLE IF NOT EXISTS</code> verwenden, um die Tabelle bei Bedarf zu erstellen.<br /></p><code version=\"2\" codelang=\"javascript\" name=\"database.js\" visible-if=\"always\"><content><text value=\"const\" class=\"keyword\" /><text value=\" Database = \" /><text value=\"require\" class=\"built_in\" /><text value=\"(\" /><text value=\"&quot;better-sqlite3&quot;\" class=\"string\" /><text value=\");\" /><text type=\"break\" /><text value=\"const\" class=\"keyword\" /><text value=\" db = \" /><text value=\"new\" class=\"keyword\" /><text value=\" Database(\" /><text value=\"&quot;database.db&quot;\" class=\"string\" /><text value=\");\" /><text type=\"break\" /><text type=\"break\" /><text value=\"db.exec(\" /><text value=\"`\" /><text type=\"break\" /><text value=\"    CREATE TABLE IF NOT EXISTS songs (\" /><text type=\"break\" /><text value=\"      id INTEGER PRIMARY KEY AUTOINCREMENT,\" /><text type=\"break\" /><text value=\"      title TEXT NOT NULL,\" /><text type=\"break\" /><text value=\"      artist TEXT NOT NULL\" /><text type=\"break\" /><text value=\"    )\" /><text type=\"break\" /><text value=\"`\" /><text value=\");\" /></content><interactions><interaction type=\"fillTheGap\" isDefault=\"true\"><options><option startIndex=\"85\" endIndex=\"87\" /><option startIndex=\"87\" endIndex=\"88\" /><option startIndex=\"88\" endIndex=\"92\" /><option startIndex=\"99\" endIndex=\"111\" /><option startIndex=\"112\" endIndex=\"125\" /></options></interaction></interactions></code><p visible-if=\"wrong\">Wähle <code>db</code>, gefolgt von <code>.</code> und schließlich <code>exec</code>, <code>CREATE TABLE</code>, <code>IF NOT EXISTS</code> aus.</p></body></html>"
          },
          {
            "title": "Lesson #3",
            "id": 132536,
            "contentType": "interactive",
            "images": [],
            "interactiveContent": "<!DOCTYPE html ><html><body><p>Zuletzt exportieren wir <code>db</code> über <code>module.exports</code>.</p><code version=\"2\" codelang=\"javascript\" name=\"database.js\" visible-if=\"always\"><content><text value=\"const\" class=\"keyword\" /><text value=\" Database = \" /><text value=\"require\" class=\"built_in\" /><text value=\"(\" /><text value=\"&quot;better-sqlite3&quot;\" class=\"string\" /><text value=\");\" /><text type=\"break\" /><text value=\"const\" class=\"keyword\" /><text value=\" db = \" /><text value=\"new\" class=\"keyword\" /><text value=\" Database(\" /><text value=\"&quot;database.db&quot;\" class=\"string\" /><text value=\");\" /><text type=\"break\" /><text type=\"break\" /><text value=\"db.exec(\" /><text value=\"`\" /><text type=\"break\" /><text value=\"    CREATE TABLE IF NOT EXISTS songs (\" /><text type=\"break\" /><text value=\"      id INTEGER PRIMARY KEY AUTOINCREMENT,\" /><text type=\"break\" /><text value=\"      title TEXT NOT NULL,\" /><text type=\"break\" /><text value=\"      artist TEXT NOT NULL\" /><text type=\"break\" /><text value=\"    )\" /><text type=\"break\" /><text value=\"`\" /><text value=\");\" /><text type=\"break\" /><text type=\"break\" /><text value=\"module\" class=\"built_in\" /><text value=\".exports = db;\" /></content><interactions><interaction type=\"fillTheGap\" isDefault=\"true\"><options><option startIndex=\"243\" endIndex=\"249\" /><option startIndex=\"249\" endIndex=\"250\" /><option startIndex=\"250\" endIndex=\"257\" /><option startIndex=\"258\" endIndex=\"259\" /><option startIndex=\"260\" endIndex=\"262\" /></options></interaction></interactions></code><p visible-if=\"wrong\">Wähle <code>module</code>, gefolgt von <code>.</code> und schließlich <code>exports</code>, <code>=</code>, <code>db</code> aus.</p></body></html>"
          },
          {
            "title": "Lesson #5",
            "id": 132538,
            "contentType": "interactive",
            "images": [],
            "interactiveContent": "<!DOCTYPE html ><html><body><p>Wir können es jetzt in unsere JavaScript-Datei importieren. Dann können wir diese Verbindung nutzen, um mit unserer Datenbank zu interagieren.</p><code version=\"2\" codelang=\"javascript\" name=\"script.js\" visible-if=\"always\"><content><text value=\"const\" class=\"keyword\" /><text value=\" db = \" /><text value=\"require\" class=\"built_in\" /><text value=\"(\" /><text value=\"&quot;./database.js&quot;\" class=\"string\" /><text value=\");\" /></content><interactions><interaction type=\"fillTheGap\" isDefault=\"true\"><options><option startIndex=\"11\" endIndex=\"18\" /><option startIndex=\"19\" endIndex=\"34\" /></options></interaction></interactions></code><code version=\"2\" codelang=\"javascript\" name=\"database.js\" visible-if=\"always\"><content><text value=\"const\" class=\"keyword\" /><text value=\" Database = \" /><text value=\"require\" class=\"built_in\" /><text value=\"(\" /><text value=\"&quot;better-sqlite3&quot;\" class=\"string\" /><text value=\");\" /><text type=\"break\" /><text value=\"const\" class=\"keyword\" /><text value=\" db = \" /><text value=\"new\" class=\"keyword\" /><text value=\" Database(\" /><text value=\"&quot;database.db&quot;\" class=\"string\" /><text value=\");\" /><text type=\"break\" /><text type=\"break\" /><text value=\"db.exec(\" /><text value=\"`\" /><text type=\"break\" /><text value=\"    CREATE TABLE IF NOT EXISTS songs (\" /><text type=\"break\" /><text value=\"      id INTEGER PRIMARY KEY AUTOINCREMENT,\" /><text type=\"break\" /><text value=\"      title TEXT NOT NULL,\" /><text type=\"break\" /><text value=\"      artist TEXT NOT NULL\" /><text type=\"break\" /><text value=\"    )\" /><text type=\"break\" /><text value=\"`\" /><text value=\");\" /><text type=\"break\" /><text type=\"break\" /><text value=\"module\" class=\"built_in\" /><text value=\".exports = db;\" /></content><output><content><text value=\"\" /><text type=\"break\" /><text value=\"/usr/lib/node_modules/better-sqlite3/lib/database.js:69\" /><text type=\"break\" /><text value=\"  [util.cppdb]: { value: new addon.Database(filename, filenameGiven, anonymous, readonly, fileMustExist, timeout, verbose || null, buffer || null) },\" /><text type=\"break\" /><text value=\"                         ^\" /><text type=\"break\" /><text value=\"SqliteError: unable to open database file\" /><text type=\"break\" /><text value=\"    at new Database (/usr/lib/node_modules/better-sqlite3/lib/database.js:69:26)\" /><text type=\"break\" /><text value=\"    at Object.&lt;anonymous&gt; (/home/default/code/file.js:2:12)\" /><text type=\"break\" /><text value=\"    at Module._compile (node:internal/modules/cjs/loader:1469:14)\" /><text type=\"break\" /><text value=\"    at Module._extensions..js (node:internal/modules/cjs/loader:1548:10)\" /><text type=\"break\" /><text value=\"    at Module.load (node:internal/modules/cjs/loader:1288:32)\" /><text type=\"break\" /><text value=\"    at Module._load (node:internal/modules/cjs/loader:1104:12)\" /><text type=\"break\" /><text value=\"    at Function.executeUserEntryPoint [as runMain] (node:internal/modules/run_main:174:12)\" /><text type=\"break\" /><text value=\"    at node:internal/main/run_main_module:28:49 {\" /><text type=\"break\" /><text value=\"  code: 'SQLITE_CANTOPEN'\" /><text type=\"break\" /><text value=\"}\" /><text type=\"break\" /><text value=\"\" /><text type=\"break\" /><text value=\"Node.js v20.17.0\" /><text type=\"break\" /><text value=\"\" /></content></output></code><p visible-if=\"wrong\">Wähle <code>require</code>, gefolgt von <code>\"./database.js\"</code> aus.</p></body></html>"
          },
          {
            "title": "Lesson #6",
            "id": 132539,
            "contentType": "interactive",
            "images": [],
            "interactiveContent": "<!DOCTYPE html ><html><body><p>Lass uns diese Verbindung nutzen, um Informationen aus unserer Datenbank abzufragen. Zuerst bereiten wir eine Anweisung vor, um Informationen zu erhalten.</p><code version=\"2\" codelang=\"javascript\" name=\"script.js\" visible-if=\"always\"><content><text value=\"const\" class=\"keyword\" /><text value=\" db = \" /><text value=\"require\" class=\"built_in\" /><text value=\"(\" /><text value=\"&quot;./database.js&quot;\" class=\"string\" /><text value=\");\" /><text type=\"break\" /><text value=\"const\" class=\"keyword\" /><text value=\" getSongsQuery = db.prepare(\" /><text value=\"&quot;SELECT * from songs&quot;\" class=\"string\" /><text value=\");\" /></content><interactions><interaction type=\"fillTheGap\" isDefault=\"true\"><options><option startIndex=\"59\" endIndex=\"61\" /><option startIndex=\"61\" endIndex=\"62\" /><option startIndex=\"62\" endIndex=\"69\" /><option startIndex=\"70\" endIndex=\"91\" /></options></interaction></interactions></code><code version=\"2\" codelang=\"javascript\" name=\"database.js\" visible-if=\"always\"><content><text value=\"const\" class=\"keyword\" /><text value=\" Database = \" /><text value=\"require\" class=\"built_in\" /><text value=\"(\" /><text value=\"&quot;better-sqlite3&quot;\" class=\"string\" /><text value=\");\" /><text type=\"break\" /><text value=\"const\" class=\"keyword\" /><text value=\" db = \" /><text value=\"new\" class=\"keyword\" /><text value=\" Database(\" /><text value=\"&quot;database.db&quot;\" class=\"string\" /><text value=\");\" /><text type=\"break\" /><text type=\"break\" /><text value=\"db.exec(\" /><text value=\"`\" /><text type=\"break\" /><text value=\"    CREATE TABLE IF NOT EXISTS songs (\" /><text type=\"break\" /><text value=\"      id INTEGER PRIMARY KEY AUTOINCREMENT,\" /><text type=\"break\" /><text value=\"      title TEXT NOT NULL,\" /><text type=\"break\" /><text value=\"      artist TEXT NOT NULL\" /><text type=\"break\" /><text value=\"    )\" /><text type=\"break\" /><text value=\"`\" /><text value=\");\" /><text type=\"break\" /><text type=\"break\" /><text value=\"module\" class=\"built_in\" /><text value=\".exports = db;\" /></content><output><content><text value=\"\" /><text type=\"break\" /><text value=\"/usr/lib/node_modules/better-sqlite3/lib/database.js:69\" /><text type=\"break\" /><text value=\"  [util.cppdb]: { value: new addon.Database(filename, filenameGiven, anonymous, readonly, fileMustExist, timeout, verbose || null, buffer || null) },\" /><text type=\"break\" /><text value=\"                         ^\" /><text type=\"break\" /><text value=\"SqliteError: unable to open database file\" /><text type=\"break\" /><text value=\"    at new Database (/usr/lib/node_modules/better-sqlite3/lib/database.js:69:26)\" /><text type=\"break\" /><text value=\"    at Object.&lt;anonymous&gt; (/home/default/code/file.js:2:12)\" /><text type=\"break\" /><text value=\"    at Module._compile (node:internal/modules/cjs/loader:1469:14)\" /><text type=\"break\" /><text value=\"    at Module._extensions..js (node:internal/modules/cjs/loader:1548:10)\" /><text type=\"break\" /><text value=\"    at Module.load (node:internal/modules/cjs/loader:1288:32)\" /><text type=\"break\" /><text value=\"    at Module._load (node:internal/modules/cjs/loader:1104:12)\" /><text type=\"break\" /><text value=\"    at Function.executeUserEntryPoint [as runMain] (node:internal/modules/run_main:174:12)\" /><text type=\"break\" /><text value=\"    at node:internal/main/run_main_module:28:49 {\" /><text type=\"break\" /><text value=\"  code: 'SQLITE_CANTOPEN'\" /><text type=\"break\" /><text value=\"}\" /><text type=\"break\" /><text value=\"\" /><text type=\"break\" /><text value=\"Node.js v20.17.0\" /><text type=\"break\" /><text value=\"\" /></content></output></code><p visible-if=\"wrong\">Wähle <code>db</code>, gefolgt von <code>.</code> und schließlich <code>prepare</code>, <code>\"SELECT * from songs\"</code> aus.</p></body></html>"
          },
          {
            "title": "Lesson #7",
            "id": 132540,
            "contentType": "interactive",
            "images": [],
            "interactiveContent": "<!DOCTYPE html ><html><body><p>Mit unserer vorbereiteten Anweisung können wir sie jetzt ausführen, um unsere Daten zu erhalten. Das tun wir, indem wir <code>all</code> auf unsere Anweisung aufrufen.</p><code version=\"2\" codelang=\"javascript\" name=\"script.js\" visible-if=\"always\"><content><text value=\"const\" class=\"keyword\" /><text value=\" db = \" /><text value=\"require\" class=\"built_in\" /><text value=\"(\" /><text value=\"&quot;./database.js&quot;\" class=\"string\" /><text value=\");\" /><text type=\"break\" /><text value=\"const\" class=\"keyword\" /><text value=\" getSongsQuery = db.prepare(\" /><text value=\"&quot;SELECT * from songs&quot;\" class=\"string\" /><text value=\");\" /><text type=\"break\" /><text value=\"const\" class=\"keyword\" /><text value=\" songs = getSongsQuery.all();\" /><text type=\"break\" /><text value=\"console\" class=\"built_in\" /><text value=\".log(songs);\" /></content><interactions><interaction type=\"fillTheGap\" isDefault=\"true\"><options><option startIndex=\"121\" endIndex=\"127\" /><option startIndex=\"108\" endIndex=\"121\" /></options></interaction></interactions><output><content><text value=\"[\" /><text type=\"break\" /><text value=\"  { id: 1, title: &quot;Bohemian Rhapsody&quot;, artist: &quot;Queen&quot; },\" /><text type=\"break\" /><text value=\"  { id: 2, title: &quot;Billie Jean&quot;, artist: &quot;Michael Jackson&quot; },\" /><text type=\"break\" /><text value=\"  { id: 3, title: &quot;Imagine&quot;, artist: &quot;John Lennon&quot; }\" /><text type=\"break\" /><text value=\"]\" /></content></output></code><code version=\"2\" codelang=\"javascript\" name=\"database.js\" visible-if=\"always\"><content><text value=\"const\" class=\"keyword\" /><text value=\" Database = \" /><text value=\"require\" class=\"built_in\" /><text value=\"(\" /><text value=\"&quot;better-sqlite3&quot;\" class=\"string\" /><text value=\");\" /><text type=\"break\" /><text value=\"const\" class=\"keyword\" /><text value=\" db = \" /><text value=\"new\" class=\"keyword\" /><text value=\" Database(\" /><text value=\"&quot;database.db&quot;\" class=\"string\" /><text value=\");\" /><text type=\"break\" /><text type=\"break\" /><text value=\"db.exec(\" /><text value=\"`\" /><text type=\"break\" /><text value=\"    CREATE TABLE IF NOT EXISTS songs (\" /><text type=\"break\" /><text value=\"      id INTEGER PRIMARY KEY AUTOINCREMENT,\" /><text type=\"break\" /><text value=\"      title TEXT NOT NULL,\" /><text type=\"break\" /><text value=\"      artist TEXT NOT NULL\" /><text type=\"break\" /><text value=\"    )\" /><text type=\"break\" /><text value=\"`\" /><text value=\");\" /><text type=\"break\" /><text type=\"break\" /><text value=\"module\" class=\"built_in\" /><text value=\".exports = db;\" /></content><output><content><text value=\"\" /><text type=\"break\" /><text value=\"/usr/lib/node_modules/better-sqlite3/lib/database.js:69\" /><text type=\"break\" /><text value=\"  [util.cppdb]: { value: new addon.Database(filename, filenameGiven, anonymous, readonly, fileMustExist, timeout, verbose || null, buffer || null) },\" /><text type=\"break\" /><text value=\"                         ^\" /><text type=\"break\" /><text value=\"SqliteError: unable to open database file\" /><text type=\"break\" /><text value=\"    at new Database (/usr/lib/node_modules/better-sqlite3/lib/database.js:69:26)\" /><text type=\"break\" /><text value=\"    at Object.&lt;anonymous&gt; (/home/default/code/file.js:2:12)\" /><text type=\"break\" /><text value=\"    at Module._compile (node:internal/modules/cjs/loader:1469:14)\" /><text type=\"break\" /><text value=\"    at Module._extensions..js (node:internal/modules/cjs/loader:1548:10)\" /><text type=\"break\" /><text value=\"    at Module.load (node:internal/modules/cjs/loader:1288:32)\" /><text type=\"break\" /><text value=\"    at Module._load (node:internal/modules/cjs/loader:1104:12)\" /><text type=\"break\" /><text value=\"    at Function.executeUserEntryPoint [as runMain] (node:internal/modules/run_main:174:12)\" /><text type=\"break\" /><text value=\"    at node:internal/main/run_main_module:28:49 {\" /><text type=\"break\" /><text value=\"  code: 'SQLITE_CANTOPEN'\" /><text type=\"break\" /><text value=\"}\" /><text type=\"break\" /><text value=\"\" /><text type=\"break\" /><text value=\"Node.js v20.17.0\" /><text type=\"break\" /><text value=\"\" /></content></output></code><p visible-if=\"wrong\">Wähle <code>getSongsQuery</code>, gefolgt von <code>.all()</code> aus.</p></body></html>"
          },
          {
            "title": "Lesson #12",
            "id": 132547,
            "contentType": "interactive",
            "images": [],
            "interactiveContent": "<!DOCTYPE html ><html><body><p>Was macht die Anweisung <code>CREATE TABLE IF NOT EXISTS</code>?</p><selection iscode=\"false\" multiple=\"multiple\"><item value=\"1\" correct=\"true\">Es erstellt eine neue Tabelle, wenn diese noch nicht existiert</item><item value=\"2\" correct=\"false\">Es überprüft, ob die Tabelle Daten enthält, bevor sie erstellt wird</item></selection><p visible-if=\"wrong\">Es erstellt eine neue Tabelle, wenn diese noch nicht existiert.</p></body></html>"
          },
          {
            "title": "Lesson #3 - Copy",
            "id": 132543,
            "contentType": "interactive",
            "images": [],
            "interactiveContent": "<!DOCTYPE html ><html><body><p>Erstelle eine Tabelle, falls sie noch nicht existiert.</p><code version=\"2\" codelang=\"javascript\" name=\"database.js\" visible-if=\"always\"><content><text value=\"const\" class=\"keyword\" /><text value=\" Database = \" /><text value=\"require\" class=\"built_in\" /><text value=\"(\" /><text value=\"&quot;better-sqlite3&quot;\" class=\"string\" /><text value=\");\" /><text type=\"break\" /><text value=\"const\" class=\"keyword\" /><text value=\" db = \" /><text value=\"new\" class=\"keyword\" /><text value=\" Database(\" /><text value=\"&quot;database.db&quot;\" class=\"string\" /><text value=\");\" /><text type=\"break\" /><text type=\"break\" /><text value=\"db.exec(\" /><text value=\"`\" /><text type=\"break\" /><text value=\"    CREATE TABLE IF NOT EXISTS companies (\" /><text type=\"break\" /><text value=\"      id INTEGER PRIMARY KEY AUTOINCREMENT,\" /><text type=\"break\" /><text value=\"      name TEXT NOT NULL\" /><text type=\"break\" /><text value=\"    )\" /><text type=\"break\" /><text value=\"`\" /><text value=\");\" /><text type=\"break\" /><text type=\"break\" /><text value=\"module\" class=\"built_in\" /><text value=\".exports = db;\" /></content><interactions><interaction type=\"fillTheGap\" isDefault=\"true\"><options><option startIndex=\"99\" endIndex=\"105\" /><option startIndex=\"106\" endIndex=\"111\" /><option startIndex=\"112\" endIndex=\"114\" /><option startIndex=\"115\" endIndex=\"118\" /><option startIndex=\"119\" endIndex=\"125\" /></options></interaction></interactions></code><p visible-if=\"wrong\">Wähle <code>CREATE</code>, gefolgt von <code>TABLE</code> und schließlich <code>IF</code>, <code>NOT</code>, <code>EXISTS</code> aus.</p></body></html>"
          },
          {
            "title": "Lesson #3 - Copy",
            "id": 132542,
            "contentType": "interactive",
            "images": [],
            "interactiveContent": "<!DOCTYPE html ><html><body><p>Exportiere die erstellte Datenbankverbindung über <code>module.export</code>.</p><code version=\"2\" codelang=\"javascript\" name=\"database.js\" visible-if=\"always\"><content><text value=\"const\" class=\"keyword\" /><text value=\" Database = \" /><text value=\"require\" class=\"built_in\" /><text value=\"(\" /><text value=\"&quot;better-sqlite3&quot;\" class=\"string\" /><text value=\");\" /><text type=\"break\" /><text value=\"const\" class=\"keyword\" /><text value=\" db = \" /><text value=\"new\" class=\"keyword\" /><text value=\" Database(\" /><text value=\"&quot;database.db&quot;\" class=\"string\" /><text value=\");\" /><text type=\"break\" /><text type=\"break\" /><text value=\"db.exec(\" /><text value=\"`\" /><text type=\"break\" /><text value=\"    CREATE TABLE IF NOT EXISTS songs (\" /><text type=\"break\" /><text value=\"      id INTEGER PRIMARY KEY AUTOINCREMENT,\" /><text type=\"break\" /><text value=\"      title TEXT NOT NULL,\" /><text type=\"break\" /><text value=\"      artist TEXT NOT NULL\" /><text type=\"break\" /><text value=\"    )\" /><text type=\"break\" /><text value=\"`\" /><text value=\");\" /><text type=\"break\" /><text type=\"break\" /><text value=\"module\" class=\"built_in\" /><text value=\".exports = db;\" /></content><interactions><interaction type=\"fillTheGap\" isDefault=\"true\"><options><option startIndex=\"243\" endIndex=\"249\" /><option startIndex=\"249\" endIndex=\"250\" /><option startIndex=\"250\" endIndex=\"257\" /><option startIndex=\"258\" endIndex=\"259\" /><option startIndex=\"260\" endIndex=\"262\" /></options></interaction></interactions></code><p visible-if=\"wrong\">Wähle <code>module</code>, gefolgt von <code>.</code> und schließlich <code>exports</code>, <code>=</code>, <code>db</code> aus.</p></body></html>"
          },
          {
            "title": "Lesson #14 - Copy",
            "id": 132551,
            "contentType": "interactive",
            "images": [],
            "interactiveContent": "<!DOCTYPE html ><html><body><p>Können wir <code>db</code> verwenden, um SQL-Abfragen auszuführen?</p><selection iscode=\"false\" multiple=\"multiple\"><item value=\"1\" correct=\"true\">Ja, wir können <code>db</code> verwenden, um entweder Abfragen in unserer Datei vorzubereiten oder auszuführen</item><item value=\"2\" correct=\"false\">Nein, alle Abfragen müssen in der <code>database.js</code>-Datei erfolgen</item></selection><code version=\"2\" codelang=\"javascript\" name=\"script.js\" visible-if=\"always\"><content><text value=\"const\" class=\"keyword\" /><text value=\" db = \" /><text value=\"require\" class=\"built_in\" /><text value=\"(\" /><text value=\"&quot;./database.js&quot;\" class=\"string\" /><text value=\");\" /></content><output><content><text value=\"node:internal/modules/cjs/loader:1228\" /><text type=\"break\" /><text value=\"  throw err;\" /><text type=\"break\" /><text value=\"  ^\" /><text type=\"break\" /><text value=\"\" /><text type=\"break\" /><text value=\"Error: Cannot find module './database.js'\" /><text type=\"break\" /><text value=\"Require stack:\" /><text type=\"break\" /><text value=\"- /home/default/code/file.js\" /><text type=\"break\" /><text value=\"    at Module._resolveFilename (node:internal/modules/cjs/loader:1225:15)\" /><text type=\"break\" /><text value=\"    at Module._load (node:internal/modules/cjs/loader:1051:27)\" /><text type=\"break\" /><text value=\"    at Module.require (node:internal/modules/cjs/loader:1311:19)\" /><text type=\"break\" /><text value=\"    at require (node:internal/modules/helpers:179:18)\" /><text type=\"break\" /><text value=\"    at Object.&lt;anonymous&gt; (/home/default/code/file.js:1:12)\" /><text type=\"break\" /><text value=\"    at Module._compile (node:internal/modules/cjs/loader:1469:14)\" /><text type=\"break\" /><text value=\"    at Module._extensions..js (node:internal/modules/cjs/loader:1548:10)\" /><text type=\"break\" /><text value=\"    at Module.load (node:internal/modules/cjs/loader:1288:32)\" /><text type=\"break\" /><text value=\"    at Module._load (node:internal/modules/cjs/loader:1104:12)\" /><text type=\"break\" /><text value=\"    at Function.executeUserEntryPoint [as runMain] (node:internal/modules/run_main:174:12) {\" /><text type=\"break\" /><text value=\"  code: 'MODULE_NOT_FOUND',\" /><text type=\"break\" /><text value=\"  requireStack: [ '/home/default/code/file.js' ]\" /><text type=\"break\" /><text value=\"}\" /><text type=\"break\" /><text value=\"\" /><text type=\"break\" /><text value=\"Node.js v20.17.0\" /><text type=\"break\" /><text value=\"\" /></content></output></code><code version=\"2\" codelang=\"javascript\" name=\"database.js\" visible-if=\"always\"><content><text value=\"const\" class=\"keyword\" /><text value=\" Database = \" /><text value=\"require\" class=\"built_in\" /><text value=\"(\" /><text value=\"&quot;better-sqlite3&quot;\" class=\"string\" /><text value=\");\" /><text type=\"break\" /><text value=\"const\" class=\"keyword\" /><text value=\" db = \" /><text value=\"new\" class=\"keyword\" /><text value=\" Database(\" /><text value=\"&quot;database.db&quot;\" class=\"string\" /><text value=\");\" /><text type=\"break\" /><text type=\"break\" /><text value=\"db.exec(\" /><text value=\"`\" /><text type=\"break\" /><text value=\"    CREATE TABLE IF NOT EXISTS songs (\" /><text type=\"break\" /><text value=\"      id INTEGER PRIMARY KEY AUTOINCREMENT,\" /><text type=\"break\" /><text value=\"      title TEXT NOT NULL,\" /><text type=\"break\" /><text value=\"      artist TEXT NOT NULL\" /><text type=\"break\" /><text value=\"    )\" /><text type=\"break\" /><text value=\"`\" /><text value=\");\" /><text type=\"break\" /><text type=\"break\" /><text value=\"module\" class=\"built_in\" /><text value=\".exports = db;\" /></content><output><content><text value=\"\" /><text type=\"break\" /><text value=\"/usr/lib/node_modules/better-sqlite3/lib/database.js:69\" /><text type=\"break\" /><text value=\"  [util.cppdb]: { value: new addon.Database(filename, filenameGiven, anonymous, readonly, fileMustExist, timeout, verbose || null, buffer || null) },\" /><text type=\"break\" /><text value=\"                         ^\" /><text type=\"break\" /><text value=\"SqliteError: unable to open database file\" /><text type=\"break\" /><text value=\"    at new Database (/usr/lib/node_modules/better-sqlite3/lib/database.js:69:26)\" /><text type=\"break\" /><text value=\"    at Object.&lt;anonymous&gt; (/home/default/code/file.js:2:12)\" /><text type=\"break\" /><text value=\"    at Module._compile (node:internal/modules/cjs/loader:1469:14)\" /><text type=\"break\" /><text value=\"    at Module._extensions..js (node:internal/modules/cjs/loader:1548:10)\" /><text type=\"break\" /><text value=\"    at Module.load (node:internal/modules/cjs/loader:1288:32)\" /><text type=\"break\" /><text value=\"    at Module._load (node:internal/modules/cjs/loader:1104:12)\" /><text type=\"break\" /><text value=\"    at Function.executeUserEntryPoint [as runMain] (node:internal/modules/run_main:174:12)\" /><text type=\"break\" /><text value=\"    at node:internal/main/run_main_module:28:49 {\" /><text type=\"break\" /><text value=\"  code: 'SQLITE_CANTOPEN'\" /><text type=\"break\" /><text value=\"}\" /><text type=\"break\" /><text value=\"\" /><text type=\"break\" /><text value=\"Node.js v20.17.0\" /><text type=\"break\" /><text value=\"\" /></content></output></code><p visible-if=\"wrong\">Ja, wir können <code>db</code> verwenden, um entweder Abfragen in unserer Datei vorzubereiten oder auszuführen.</p></body></html>"
          },
          {
            "title": "Lesson #13",
            "id": 132548,
            "contentType": "interactive",
            "images": [],
            "interactiveContent": "<!DOCTYPE html ><html><body><p>Was wird von dieser Datei exportiert?</p><code version=\"2\" codelang=\"javascript\" name=\"database.js\" visible-if=\"always\"><content><text value=\"const\" class=\"keyword\" /><text value=\" Database = \" /><text value=\"require\" class=\"built_in\" /><text value=\"(\" /><text value=\"&quot;better-sqlite3&quot;\" class=\"string\" /><text value=\");\" /><text type=\"break\" /><text value=\"const\" class=\"keyword\" /><text value=\" db = \" /><text value=\"new\" class=\"keyword\" /><text value=\" Database(\" /><text value=\"&quot;database.db&quot;\" class=\"string\" /><text value=\");\" /><text type=\"break\" /><text type=\"break\" /><text value=\"db.exec(\" /><text value=\"`\" /><text type=\"break\" /><text value=\"    CREATE TABLE IF NOT EXISTS friends (\" /><text type=\"break\" /><text value=\"      id INTEGER PRIMARY KEY AUTOINCREMENT,\" /><text type=\"break\" /><text value=\"      name TEXT NOT NULL\" /><text type=\"break\" /><text value=\"    )\" /><text type=\"break\" /><text value=\"`\" /><text value=\");\" /><text type=\"break\" /><text type=\"break\" /><text value=\"module\" class=\"built_in\" /><text value=\".exports = db;\" /></content></code><selection iscode=\"false\" multiple=\"multiple\"><item value=\"1\" correct=\"true\">Das <code>db</code>-Objekt, das die Verbindung zur SQLite-Datenbank darstellt</item><item value=\"2\" correct=\"false\">Eine Funktion, um SQL-Abfragen direkt auszuführen</item></selection><p visible-if=\"wrong\">Das <code>db</code>-Objekt, das die Verbindung zur SQLite-Datenbank darstellt.</p></body></html>"
          },
          {
            "title": "Lesson #7 - Copy",
            "id": 132545,
            "contentType": "interactive",
            "images": [],
            "interactiveContent": "<!DOCTYPE html ><html><body><p>Verwende das importierte <code>db</code>, um ein SQL-Statement vorzubereiten.</p><code version=\"2\" codelang=\"javascript\" name=\"script.js\" visible-if=\"always\"><content><text value=\"const\" class=\"keyword\" /><text value=\" db = \" /><text value=\"require\" class=\"built_in\" /><text value=\"(\" /><text value=\"&quot;./database.js&quot;\" class=\"string\" /><text value=\");\" /><text type=\"break\" /><text value=\"const\" class=\"keyword\" /><text value=\" getSongsQuery = db.prepare(\" /><text value=\"&quot;SELECT * from songs&quot;\" class=\"string\" /><text value=\");\" /><text type=\"break\" /><text value=\"const\" class=\"keyword\" /><text value=\" songs = getSongsQuery.all();\" /><text type=\"break\" /><text value=\"console\" class=\"built_in\" /><text value=\".log(songs);\" /></content><interactions><interaction type=\"fillTheGap\" isDefault=\"true\"><options><option startIndex=\"6\" endIndex=\"8\" /><option startIndex=\"59\" endIndex=\"61\" /><option startIndex=\"61\" endIndex=\"62\" /><option startIndex=\"62\" endIndex=\"69\" /><option startIndex=\"70\" endIndex=\"91\" /></options></interaction></interactions><output><content><text value=\"[\" /><text type=\"break\" /><text value=\"  { id: 1, title: &quot;Bohemian Rhapsody&quot;, artist: &quot;Queen&quot; },\" /><text type=\"break\" /><text value=\"  { id: 2, title: &quot;Billie Jean&quot;, artist: &quot;Michael Jackson&quot; },\" /><text type=\"break\" /><text value=\"  { id: 3, title: &quot;Imagine&quot;, artist: &quot;John Lennon&quot; }\" /><text type=\"break\" /><text value=\"]\" /></content></output></code><code version=\"2\" codelang=\"javascript\" name=\"database.js\" visible-if=\"always\"><content><text value=\"const\" class=\"keyword\" /><text value=\" Database = \" /><text value=\"require\" class=\"built_in\" /><text value=\"(\" /><text value=\"&quot;better-sqlite3&quot;\" class=\"string\" /><text value=\");\" /><text type=\"break\" /><text value=\"const\" class=\"keyword\" /><text value=\" db = \" /><text value=\"new\" class=\"keyword\" /><text value=\" Database(\" /><text value=\"&quot;database.db&quot;\" class=\"string\" /><text value=\");\" /><text type=\"break\" /><text type=\"break\" /><text value=\"db.exec(\" /><text value=\"`\" /><text type=\"break\" /><text value=\"    CREATE TABLE IF NOT EXISTS songs (\" /><text type=\"break\" /><text value=\"      id INTEGER PRIMARY KEY AUTOINCREMENT,\" /><text type=\"break\" /><text value=\"      title TEXT NOT NULL,\" /><text type=\"break\" /><text value=\"      artist TEXT NOT NULL\" /><text type=\"break\" /><text value=\"    )\" /><text type=\"break\" /><text value=\"`\" /><text value=\");\" /><text type=\"break\" /><text type=\"break\" /><text value=\"module\" class=\"built_in\" /><text value=\".exports = db;\" /></content><output><content><text value=\"\" /><text type=\"break\" /><text value=\"/usr/lib/node_modules/better-sqlite3/lib/database.js:69\" /><text type=\"break\" /><text value=\"  [util.cppdb]: { value: new addon.Database(filename, filenameGiven, anonymous, readonly, fileMustExist, timeout, verbose || null, buffer || null) },\" /><text type=\"break\" /><text value=\"                         ^\" /><text type=\"break\" /><text value=\"SqliteError: unable to open database file\" /><text type=\"break\" /><text value=\"    at new Database (/usr/lib/node_modules/better-sqlite3/lib/database.js:69:26)\" /><text type=\"break\" /><text value=\"    at Object.&lt;anonymous&gt; (/home/default/code/file.js:2:12)\" /><text type=\"break\" /><text value=\"    at Module._compile (node:internal/modules/cjs/loader:1469:14)\" /><text type=\"break\" /><text value=\"    at Module._extensions..js (node:internal/modules/cjs/loader:1548:10)\" /><text type=\"break\" /><text value=\"    at Module.load (node:internal/modules/cjs/loader:1288:32)\" /><text type=\"break\" /><text value=\"    at Module._load (node:internal/modules/cjs/loader:1104:12)\" /><text type=\"break\" /><text value=\"    at Function.executeUserEntryPoint [as runMain] (node:internal/modules/run_main:174:12)\" /><text type=\"break\" /><text value=\"    at node:internal/main/run_main_module:28:49 {\" /><text type=\"break\" /><text value=\"  code: 'SQLITE_CANTOPEN'\" /><text type=\"break\" /><text value=\"}\" /><text type=\"break\" /><text value=\"\" /><text type=\"break\" /><text value=\"Node.js v20.17.0\" /><text type=\"break\" /><text value=\"\" /></content></output></code><p visible-if=\"wrong\">Wähle <code>db</code>, gefolgt von <code>db</code> und schließlich <code>.</code>, <code>prepare</code>, <code>\"SELECT * from songs\"</code> aus.</p></body></html>"
          },
          {
            "title": "Lesson #14",
            "id": 132549,
            "contentType": "interactive",
            "images": [],
            "interactiveContent": "<!DOCTYPE html ><html><body><p>Was macht <code>require(\"./database.js\")</code> in dieser Datei?</p><selection iscode=\"false\" multiple=\"multiple\"><item value=\"1\" correct=\"true\">Es importiert die Datenbankverbindung aus <code>database.js</code></item><item value=\"2\" correct=\"false\">Es importiert eine Funktion, um SQL-Abfragen auszuführen</item></selection><code version=\"2\" codelang=\"javascript\" name=\"script.js\" visible-if=\"always\"><content><text value=\"const\" class=\"keyword\" /><text value=\" db = \" /><text value=\"require\" class=\"built_in\" /><text value=\"(\" /><text value=\"&quot;./database.js&quot;\" class=\"string\" /><text value=\");\" /></content><output><content><text value=\"node:internal/modules/cjs/loader:1228\" /><text type=\"break\" /><text value=\"  throw err;\" /><text type=\"break\" /><text value=\"  ^\" /><text type=\"break\" /><text value=\"\" /><text type=\"break\" /><text value=\"Error: Cannot find module './database.js'\" /><text type=\"break\" /><text value=\"Require stack:\" /><text type=\"break\" /><text value=\"- /home/default/code/file.js\" /><text type=\"break\" /><text value=\"    at Module._resolveFilename (node:internal/modules/cjs/loader:1225:15)\" /><text type=\"break\" /><text value=\"    at Module._load (node:internal/modules/cjs/loader:1051:27)\" /><text type=\"break\" /><text value=\"    at Module.require (node:internal/modules/cjs/loader:1311:19)\" /><text type=\"break\" /><text value=\"    at require (node:internal/modules/helpers:179:18)\" /><text type=\"break\" /><text value=\"    at Object.&lt;anonymous&gt; (/home/default/code/file.js:1:12)\" /><text type=\"break\" /><text value=\"    at Module._compile (node:internal/modules/cjs/loader:1469:14)\" /><text type=\"break\" /><text value=\"    at Module._extensions..js (node:internal/modules/cjs/loader:1548:10)\" /><text type=\"break\" /><text value=\"    at Module.load (node:internal/modules/cjs/loader:1288:32)\" /><text type=\"break\" /><text value=\"    at Module._load (node:internal/modules/cjs/loader:1104:12)\" /><text type=\"break\" /><text value=\"    at Function.executeUserEntryPoint [as runMain] (node:internal/modules/run_main:174:12) {\" /><text type=\"break\" /><text value=\"  code: 'MODULE_NOT_FOUND',\" /><text type=\"break\" /><text value=\"  requireStack: [ '/home/default/code/file.js' ]\" /><text type=\"break\" /><text value=\"}\" /><text type=\"break\" /><text value=\"\" /><text type=\"break\" /><text value=\"Node.js v20.17.0\" /><text type=\"break\" /><text value=\"\" /></content></output></code><code version=\"2\" codelang=\"javascript\" name=\"database.js\" visible-if=\"always\"><content><text value=\"const\" class=\"keyword\" /><text value=\" Database = \" /><text value=\"require\" class=\"built_in\" /><text value=\"(\" /><text value=\"&quot;better-sqlite3&quot;\" class=\"string\" /><text value=\");\" /><text type=\"break\" /><text value=\"const\" class=\"keyword\" /><text value=\" db = \" /><text value=\"new\" class=\"keyword\" /><text value=\" Database(\" /><text value=\"&quot;database.db&quot;\" class=\"string\" /><text value=\");\" /><text type=\"break\" /><text type=\"break\" /><text value=\"db.exec(\" /><text value=\"`\" /><text type=\"break\" /><text value=\"    CREATE TABLE IF NOT EXISTS songs (\" /><text type=\"break\" /><text value=\"      id INTEGER PRIMARY KEY AUTOINCREMENT,\" /><text type=\"break\" /><text value=\"      title TEXT NOT NULL,\" /><text type=\"break\" /><text value=\"      artist TEXT NOT NULL\" /><text type=\"break\" /><text value=\"    )\" /><text type=\"break\" /><text value=\"`\" /><text value=\");\" /><text type=\"break\" /><text type=\"break\" /><text value=\"module\" class=\"built_in\" /><text value=\".exports = db;\" /></content><output><content><text value=\"\" /><text type=\"break\" /><text value=\"/usr/lib/node_modules/better-sqlite3/lib/database.js:69\" /><text type=\"break\" /><text value=\"  [util.cppdb]: { value: new addon.Database(filename, filenameGiven, anonymous, readonly, fileMustExist, timeout, verbose || null, buffer || null) },\" /><text type=\"break\" /><text value=\"                         ^\" /><text type=\"break\" /><text value=\"SqliteError: unable to open database file\" /><text type=\"break\" /><text value=\"    at new Database (/usr/lib/node_modules/better-sqlite3/lib/database.js:69:26)\" /><text type=\"break\" /><text value=\"    at Object.&lt;anonymous&gt; (/home/default/code/file.js:2:12)\" /><text type=\"break\" /><text value=\"    at Module._compile (node:internal/modules/cjs/loader:1469:14)\" /><text type=\"break\" /><text value=\"    at Module._extensions..js (node:internal/modules/cjs/loader:1548:10)\" /><text type=\"break\" /><text value=\"    at Module.load (node:internal/modules/cjs/loader:1288:32)\" /><text type=\"break\" /><text value=\"    at Module._load (node:internal/modules/cjs/loader:1104:12)\" /><text type=\"break\" /><text value=\"    at Function.executeUserEntryPoint [as runMain] (node:internal/modules/run_main:174:12)\" /><text type=\"break\" /><text value=\"    at node:internal/main/run_main_module:28:49 {\" /><text type=\"break\" /><text value=\"  code: 'SQLITE_CANTOPEN'\" /><text type=\"break\" /><text value=\"}\" /><text type=\"break\" /><text value=\"\" /><text type=\"break\" /><text value=\"Node.js v20.17.0\" /><text type=\"break\" /><text value=\"\" /></content></output></code><p visible-if=\"wrong\">Es importiert die Datenbankverbindung aus <code>database.js</code>.</p></body></html>"
          }
        ]
      }
    ]
  }
}